setup.py
eru_res.egg-info/PKG-INFO
eru_res.egg-info/SOURCES.txt
eru_res.egg-info/dependency_links.txt
eru_res.egg-info/entry_points.txt
eru_res.egg-info/not-zip-safe
eru_res.egg-info/requires.txt
eru_res.egg-info/top_level.txt
res/__init__.py
res/cmdline/__init__.py
res/cmdline/console.py
res/cmdline/influxdb.py
res/cmdline/nginx.py
res/cmdline/sentry.py
res/ext/__init__.py
res/ext/common.py
res/ext/influxdb.py
res/ext/nginx.py
res/ext/sentry.py
res/libs/__init__.py
res/libs/colorlog.py
res/libs/scp.py
res/libs/ssh.py
res/utils/__init__.py
res/utils/helper.py