Metadata-Version: 1.0
Name: eru-res
Version: 0.0.1
Summary: NBE resource tool
Home-page: http://git.hunantv.com
Author: CMGS
Author-email: ilskdw@gmail.com
License: BSD
Keywords: influxdb mysql
Platform: UNKNOWN
